qonnx/__init__.py
qonnx/analysis/__init__.py
qonnx/analysis/base.py
qonnx/analysis/inference_cost.py
qonnx/analysis/tensor_stats.py
qonnx/analysis/topology.py
qonnx/converters/__init__.py
qonnx/converters/keras.py
qonnx/converters/qkeras/__init__.py
qonnx/converters/qkeras/onnx.py
qonnx/converters/qkeras/qlayers.py
qonnx/converters/qkeras/quantizers.py
qonnx/core/__init__.py
qonnx/core/data_layout.py
qonnx/core/datatype.py
qonnx/core/execute_custom_node.py
qonnx/core/modelwrapper.py
qonnx/core/onnx_exec.py
qonnx/custom_op/__init__.py
qonnx/custom_op/base.py
qonnx/custom_op/registry.py
qonnx/custom_op/channels_last/__init__.py
qonnx/custom_op/channels_last/base_wrapped_op.py
qonnx/custom_op/channels_last/batch_normalization.py
qonnx/custom_op/channels_last/conv.py
qonnx/custom_op/channels_last/max_pool.py
qonnx/custom_op/general/__init__.py
qonnx/custom_op/general/bipolar_quant.py
qonnx/custom_op/general/debugmarker.py
qonnx/custom_op/general/genericpartition.py
qonnx/custom_op/general/im2col.py
qonnx/custom_op/general/maxpoolnhwc.py
qonnx/custom_op/general/multithreshold.py
qonnx/custom_op/general/quant.py
qonnx/custom_op/general/quantavgpool2d.py
qonnx/custom_op/general/trunc.py
qonnx/custom_op/general/xnorpopcount.py
qonnx/data/__init__.py
qonnx/data/onnx/eltwise_chanlast_testcase.onnx
qonnx/data/onnx/residual_block_clean.onnx
qonnx/data/onnx/bsd300x3-espcn/nn_resize/float_model.onnx
qonnx/data/onnx/bsd300x3-espcn/nn_resize/quant_model.onnx
qonnx/data/onnx/bsd300x3-espcn/subpixel/float_model.onnx
qonnx/data/onnx/bsd300x3-espcn/subpixel/quant_model.onnx
qonnx/data/onnx/bsd300x3-espcn/test_data/input_0.pb
qonnx/data/onnx/matmul_update/sdp.onnx
qonnx/data/onnx/mnist-conv/README.md
qonnx/data/onnx/mnist-conv/model.onnx
qonnx/data/onnx/mnist-conv/test_data_set_0/input_0.pb
qonnx/data/onnx/mnist-conv/test_data_set_0/output_0.pb
qonnx/transformation/__init__.py
qonnx/transformation/base.py
qonnx/transformation/batchnorm_to_affine.py
qonnx-0.4.0.dist-info/AUTHORS.rst
qonnx-0.4.0.dist-info/LICENSE
qonnx-0.4.0.dist-info/METADATA
qonnx-0.4.0.dist-info/WHEEL
qonnx-0.4.0.dist-info/entry_points.txt
qonnx-0.4.0.dist-info/top_level.txt
qonnx-0.4.0.dist-info/RECORD
