Metadata-Version: 2.1
Name: qonnx
Version: 0.4.0
Summary: Frontend and utilities for QONNX
Home-page: https://github.com/fastmachinelearning/qonnx
License: Apache-2.0
Project-URL: Documentation, https://pyscaffold.org/
Platform: any
Classifier: Development Status :: 4 - Beta
Classifier: Programming Language :: Python
Requires-Dist: attrs>=22.2.0
Requires-Dist: clize>=5.0.1
Requires-Dist: protobuf==3.20.3
Requires-Dist: bitstring>=3.1.7
Requires-Dist: numpy>=1.24.1
Requires-Dist: onnx>=1.13.0
Requires-Dist: onnxruntime>=1.16.1
Requires-Dist: sigtools>=4.0.1
Requires-Dist: toposort>=1.7.0
Requires-Dist: importlib-metadata; python_version < "3.8"
Provides-Extra: notebooks
Requires-Dist: jupyter; extra == "notebooks"
Requires-Dist: netron; extra == "notebooks"
Provides-Extra: qkeras
Requires-Dist: pyparsing; extra == "qkeras"
Requires-Dist: tf2onnx>=1.16.1; extra == "qkeras"
Requires-Dist: tensorflow<=2.14.1,>=2.9.0; extra == "qkeras"
Requires-Dist: QKeras>=0.9.0; extra == "qkeras"
Provides-Extra: testing
Requires-Dist: setuptools; extra == "testing"
Requires-Dist: pytest; extra == "testing"
Requires-Dist: pytest-xdist; extra == "testing"
Requires-Dist: pytest-cov; extra == "testing"
Requires-Dist: pytest-randomly; extra == "testing"
